flespi_gateway/__init__.py
flespi_gateway/gateway.py
flespi_gateway/logger.py
flespi_gateway/utils.py
flespi_gateway-0.0.8.dist-info/LICENSE
flespi_gateway-0.0.8.dist-info/METADATA
flespi_gateway-0.0.8.dist-info/WHEEL
flespi_gateway-0.0.8.dist-info/top_level.txt
flespi_gateway-0.0.8.dist-info/RECORD
